face_preprocessor/__init__.py
face_preprocessor/config.py
face_preprocessor/detector.py
face_preprocessor/processor.py
face_preprocessor/utils.py
face_preprocessor-0.0.1.dist-info/LICENSE
face_preprocessor-0.0.1.dist-info/METADATA
face_preprocessor-0.0.1.dist-info/WHEEL
face_preprocessor-0.0.1.dist-info/top_level.txt
face_preprocessor-0.0.1.dist-info/RECORD
